fenn/__init__.py
fenn/args/__init__.py
fenn/args/parser.py
fenn/cli/__init__.py
fenn/cli/list.py
fenn/cli/pull.py
fenn/cli/utils.py
fenn/core/__init__.py
fenn/core/fenn.py
fenn/datasets/__init__.py
fenn/datasets/text_dataset.py
fenn/experimental/transformers/__init__.py
fenn/experimental/transformers/lora_config.py
fenn/experimental/transformers/sequence_classifier.py
fenn/experimental/vision/__init__.py
fenn/experimental/vision/color_mode.py
fenn/experimental/vision/image_batch_check.py
fenn/experimental/vision/image_dir_summary.py
fenn/experimental/vision/resize.py
fenn/experimental/vision/summary.py
fenn/experimental/vision/vision_utils.py
fenn/logging/__init__.py
fenn/logging/logger.py
fenn/logging/backends/logging.py
fenn/logging/backends/tensorboard.py
fenn/logging/backends/wandb.py
fenn/nn/__init__.py
fenn/nn/trainers/__init__.py
fenn/nn/trainers/trainer.py
fenn/notification/__init__.py
fenn/notification/notifier.py
fenn/notification/service.py
fenn/notification/services/__init__.py
fenn/notification/services/discord.py
fenn/notification/services/resend.py
fenn/notification/services/slack.py
fenn/notification/services/telegram.py
fenn/secrets/__init__.py
fenn/secrets/keystore.py
fenn/utils/__init__.py
fenn-0.1.1.dist-info/licenses/LICENSE
tests/conftest.py
tests/cli/test_pull_command.py
tests/notification/test_discord_service.py
tests/notification/test_resend_service.py
tests/notification/test_slack_service.py
tests/vision/test_color_mode.py
tests/vision/test_image_batch_check.py
tests/vision/test_image_dir_summary.py
tests/vision/test_resize.py
tests/vision/test_summary.py
tests/vision/test_vision_utils.py
fenn-0.1.1.dist-info/METADATA
fenn-0.1.1.dist-info/WHEEL
fenn-0.1.1.dist-info/entry_points.txt
fenn-0.1.1.dist-info/top_level.txt
fenn-0.1.1.dist-info/RECORD
