Metadata-Version: 2.4
Name: fenn
Version: 0.1.1
Summary: Friendly Environment for Neural Networks – a simple framework that automates the boring side of ML.
Author-email: Alessio Russo <alessio.russo.ar98@gmail.com>
Project-URL: Homepage, https://pyfenn.org
Project-URL: Documentation, https://pyfenn.org
Project-URL: Source Code, https://github.com/blkdmr/fenn
Project-URL: Bug Tracker, https://github.com/blkdmr/fenn/issues
Classifier: Development Status :: 3 - Alpha
Classifier: Intended Audience :: Developers
Classifier: Intended Audience :: Science/Research
Classifier: Topic :: Scientific/Engineering :: Artificial Intelligence
Classifier: Topic :: Scientific/Engineering :: Information Analysis
Classifier: License :: OSI Approved :: MIT License
Classifier: Programming Language :: Python
Classifier: Programming Language :: Python :: 3
Classifier: Programming Language :: Python :: 3.10
Classifier: Programming Language :: Python :: 3.11
Classifier: Programming Language :: Python :: 3.12
Classifier: Operating System :: OS Independent
Requires-Python: >=3.11
License-File: LICENSE
Requires-Dist: PyYAML>=6.0.3
Requires-Dist: wandb>=0.23.0
Requires-Dist: numpy<2.3.0,>=2
Requires-Dist: pandas>=2.3.3
Requires-Dist: matplotlib>=3.10.7
Requires-Dist: scikit-learn>=1.7.2
Requires-Dist: colorama>=0.4.6
Requires-Dist: requests>=2.32.5
Requires-Dist: python-dotenv>=1.2.1
Requires-Dist: resend>=2.0.0
Provides-Extra: torch
Requires-Dist: torch>=2.9.1; extra == "torch"
Requires-Dist: torchvision>=0.24.1; extra == "torch"
Provides-Extra: vision
Requires-Dist: Pillow>=10.0.0; extra == "vision"
Requires-Dist: torch>=2.9.1; extra == "vision"
Requires-Dist: torchvision>=0.24.1; extra == "vision"
Provides-Extra: transformers
Requires-Dist: peft~=0.18.0; extra == "transformers"
Requires-Dist: transformers~=4.57.3; extra == "transformers"
Provides-Extra: test
Requires-Dist: pytest>=8.0.0; extra == "test"
Requires-Dist: pytest-cov>=7.0.0; extra == "test"
Requires-Dist: requests-mock>=1.11.0; extra == "test"
Requires-Dist: Faker>=25.0.0; extra == "test"
Dynamic: license-file
